<PAMDataset>
  <Metadata domain="Esri">
    <MDI key="PyramidResamplingType">NEAREST</MDI>
  </Metadata>
  <PAMRasterBand band="1">
    <Histograms>
      <HistItem>
        <HistMin>-0.5</HistMin>
        <HistMax>181.5</HistMax>
        <BucketCount>182</BucketCount>
        <IncludeOutOfRange>1</IncludeOutOfRange>
        <Approximate>0</Approximate>
        <HistCounts>100070633|5958852|4694308|2642019|4309620|2245948|1629892|2324709|0|1370840|516059|237912|21959|2442274|490195|3202328|2021516|1562654|1676186|0|0|0|13314|212401|0|7302|0|2430|227108|145038|0|36722|0|43857|263397|0|0|0|0|0|86460|0|0|0|394997|0|0|81|0|745846|0|0|0|78505|123204|0|0|0|0|146358|1414|0|7389|0|77826|0|3727|0|0|0|0|68762|0|0|0|0|0|19202|0|0|0|0|0|13277|0|0|58851|0|0|0|0|0|0|0|0|0|9674|0|0|0|0|55374|71001|181735|0|0|0|0|0|0|150129|0|0|0|23094|0|0|0|0|0|17953|0|10740|0|0|46348|0|0|0|72354|0|0|0|0|0|0|0|0|0|15755|0|0|0|274|0|0|0|0|0|0|102792|15192|20120|0|0|0|0|0|0|0|0|0|0|0|0|0|0|0|0|0|0|0|0|0|4487|0|0|0|0|0|0|2956</HistCounts>
      </HistItem>
      <HistItem>
        <HistMin>-0.4972527472527473</HistMin>
        <HistMax>181.4972527472528</HistMax>
        <BucketCount>182</BucketCount>
        <IncludeOutOfRange>0</IncludeOutOfRange>
        <Approximate>0</Approximate>
        <HistCounts>100070633|5958852|4694308|2642019|4309620|2245948|1629892|2324709|0|1370840|516059|237912|21959|2442274|490195|3202328|2021516|1562654|1676186|0|0|0|13314|212401|0|7302|0|2430|227108|145038|0|36722|0|43857|263397|0|0|0|0|0|86460|0|0|0|394997|0|0|81|0|745846|0|0|0|78505|123204|0|0|0|0|146358|1414|0|7389|0|77826|0|3727|0|0|0|0|68762|0|0|0|0|0|19202|0|0|0|0|0|13277|0|0|58851|0|0|0|0|0|0|0|0|0|9674|0|0|0|0|55374|71001|181735|0|0|0|0|0|0|150129|0|0|0|23094|0|0|0|0|0|17953|0|10740|0|0|46348|0|0|0|72354|0|0|0|0|0|0|0|0|0|15755|0|0|0|274|0|0|0|0|0|0|102792|15192|20120|0|0|0|0|0|0|0|0|0|0|0|0|0|0|0|0|0|0|0|0|0|4487|0|0|0|0|0|0|2956</HistCounts>
      </HistItem>
      <HistItem>
        <HistMin>-0.498046875</HistMin>
        <HistMax>255.498046875</HistMax>
        <BucketCount>256</BucketCount>
        <IncludeOutOfRange>0</IncludeOutOfRange>
        <Approximate>1</Approximate>
        <HistCounts>70810|7032|945|696|2448|1565|256|99|0|2732|239|142|0|0|132|640|1142|3523|62|0|0|0|0|0|0|0|0|0|39|101|0|0|0|0|4|0|0|0|0|0|125|0|0|0|1|0|0|0|0|0|0|0|0|0|0|0|0|0|0|101|0|0|0|0|0|0|0|0|0|0|0|67|0|0|0|0|0|0|0|0|0|0|0|0|0|0|0|0|0|0|0|0|0|0|0|0|0|0|0|0|0|0|0|0|0|0|0|0|0|0|10|0|0|0|0|0|0|0|0|0|0|0|0|0|0|0|0|0|0|0|0|0|0|0|0|0|0|0|0|0|0|0|0|0|0|0|0|0|0|0|17|0|0|0|0|0|0|0|0|0|0|0|0|0|0|0|0|0|0|0|0|0|0|0|0|0|0|0|0|0|0|0|0|0|0|0|0|0|0|0|0|0|0|0|0|0|0|0|0|0|0|0|0|0|0|0|0|0|0|0|0|0|0|0|0|0|0|0|0|0|0|0|0|0|0|0|0|0|0|0|0|0|0|0|0|0|0|0|0|0|0|0|0|0|0|0|0|0|0|0|0|0|0|0|0|0</HistCounts>
      </HistItem>
    </Histograms>
    <Metadata>
      <MDI key="RepresentationType">THEMATIC</MDI>
      <MDI key="STATISTICS_COUNT">140995350.000000</MDI>
      <MDI key="STATISTICS_COVARIANCES">134.5737182144763</MDI>
      <MDI key="STATISTICS_MAXIMUM">181</MDI>
      <MDI key="STATISTICS_MEAN">3.4831025349418</MDI>
      <MDI key="STATISTICS_MEDIAN">0.000000</MDI>
      <MDI key="STATISTICS_MINIMUM">0</MDI>
      <MDI key="STATISTICS_SKIPFACTORX">1</MDI>
      <MDI key="STATISTICS_SKIPFACTORY">1</MDI>
      <MDI key="STATISTICS_STDDEV">11.600591246146</MDI>
      <MDI key="STATISTICS_VALID_PERCENT">100</MDI>
    </Metadata>
  </PAMRasterBand>
</PAMDataset>
